articleDateExtractor/__init__.py
articleDateExtractor-0.20.dist-info/DESCRIPTION.rst
articleDateExtractor-0.20.dist-info/METADATA
articleDateExtractor-0.20.dist-info/RECORD
articleDateExtractor-0.20.dist-info/WHEEL
articleDateExtractor-0.20.dist-info/metadata.json
articleDateExtractor-0.20.dist-info/top_level.txt
