Metadata-Version: 2.0
Name: articleDateExtractor
Version: 0.20
Summary: Automatically extracts and normalizes an online article or blog post publication date
Home-page: https://github.com/Webhose/article-date-extractor
Author: Ran Geva
Author-email: ran@webhose.io, yitao.sun@yahoo.com, wilson.s.shilo@gmail.com
License: MIT
Platform: UNKNOWN
Classifier: Development Status :: 4 - Beta
Classifier: Intended Audience :: Developers
Classifier: Natural Language :: English
Classifier: License :: OSI Approved :: MIT License
Classifier: Programming Language :: Python
Classifier: Programming Language :: Python :: 2.6
Classifier: Programming Language :: Python :: 2.7
Classifier: Programming Language :: Python :: 3
Classifier: Programming Language :: Python :: 3.5
Classifier: Programming Language :: Python :: 3.6
Requires-Dist: beautifulsoup4 (>=4.6.0)
Requires-Dist: python-dateutil (>=2.4.2)
